{"page":154,"lines":{"1":[{"c":"´¡æ ´¡Æ","t":"word","k":"7:31","v":31},{"c":"´¡ô","t":"word","k":"7:31","v":31},{"c":"´¡ö","t":"word","k":"7:31","v":31},{"c":"´¡ò","t":"word","k":"7:31","v":31},{"c":"´¡û","t":"word","k":"7:31","v":31},{"c":"´¡ù","t":"word","k":"7:31","v":31},{"c":"´¡ÿ","t":"word","k":"7:31","v":31},{"c":"´¡Ö","t":"word","k":"7:31","v":31},{"c":"´¡Ü","t":"word","k":"7:31","v":31}],"2":[{"c":"´¡ø","t":"word","k":"7:31","v":31},{"c":"´¡£´¡Ø","t":"word","k":"7:31","v":31},{"c":"´¡×","t":"word","k":"7:31","v":31},{"c":"´¡ƒ","t":"word","k":"7:31","v":31},{"c":"´¡á","t":"word","k":"7:31","v":31},{"c":"´¡í","t":"word","k":"7:31","v":31},{"c":"´¡ó","t":"end","k":"7:31","v":31},{"c":"´¡ú","t":"word","k":"7:32","v":32},{"c":"´¡ñ","t":"word","k":"7:32","v":32},{"c":"´¡Ñ","t":"word","k":"7:32","v":32},{"c":"´¡ª","t":"word","k":"7:32","v":32},{"c":"´¡º","t":"word","k":"7:32","v":32}],"3":[{"c":"´¡¿","t":"word","k":"7:32","v":32},{"c":"´¡®","t":"word","k":"7:32","v":32},{"c":"´¡¬","t":"word","k":"7:32","v":32},{"c":"´¡½","t":"word","k":"7:32","v":32},{"c":"´¡¼","t":"word","k":"7:32","v":32},{"c":"´¡¡´¡«","t":"word","k":"7:32","v":32},{"c":"´¡»","t":"word","k":"7:32","v":32},{"c":"´¡░","t":"word","k":"7:32","v":32},{"c":"´¡▒","t":"word","k":"7:32","v":32},{"c":"´¡▓","t":"word","k":"7:32","v":32}],"4":[{"c":"´¡│","t":"word","k":"7:32","v":32},{"c":"´¡┤","t":"word","k":"7:32","v":32},{"c":"´¡Á","t":"word","k":"7:32","v":32},{"c":"´¡Â","t":"word","k":"7:32","v":32},{"c":"´¡À","t":"word","k":"7:32","v":32},{"c":"´¡©´¡╣","t":"word","k":"7:32","v":32},{"c":"´¡║","t":"word","k":"7:32","v":32},{"c":"´¡╗","t":"word","k":"7:32","v":32},{"c":"´¡╝","t":"word","k":"7:32","v":32}],"5":[{"c":"´¡¢","t":"word","k":"7:32","v":32},{"c":"´¡¥","t":"word","k":"7:32","v":32},{"c":"´¡┐","t":"end","k":"7:32","v":32},{"c":"´«Ç","t":"word","k":"7:33","v":33},{"c":"´«ü","t":"word","k":"7:33","v":33},{"c":"´«é","t":"word","k":"7:33","v":33},{"c":"´«â","t":"word","k":"7:33","v":33},{"c":"´«ä","t":"word","k":"7:33","v":33},{"c":"´«à","t":"word","k":"7:33","v":33},{"c":"´«å","t":"word","k":"7:33","v":33},{"c":"´«ç","t":"word","k":"7:33","v":33},{"c":"´«ê","t":"word","k":"7:33","v":33}],"6":[{"c":"´«ë","t":"word","k":"7:33","v":33},{"c":"´«è","t":"word","k":"7:33","v":33},{"c":"´«ï","t":"word","k":"7:33","v":33},{"c":"´«î","t":"word","k":"7:33","v":33},{"c":"´«ì","t":"word","k":"7:33","v":33},{"c":"´«Ä","t":"word","k":"7:33","v":33},{"c":"´«Å","t":"word","k":"7:33","v":33},{"c":"´«É","t":"word","k":"7:33","v":33},{"c":"´«æ","t":"word","k":"7:33","v":33},{"c":"´«Æ","t":"word","k":"7:33","v":33},{"c":"´«ô","t":"word","k":"7:33","v":33},{"c":"´«ö","t":"word","k":"7:33","v":33}],"7":[{"c":"´«ò","t":"word","k":"7:33","v":33},{"c":"´«û","t":"word","k":"7:33","v":33},{"c":"´«ù","t":"word","k":"7:33","v":33},{"c":"´«ÿ","t":"word","k":"7:33","v":33},{"c":"´«Ö","t":"word","k":"7:33","v":33},{"c":"´«Ü","t":"word","k":"7:33","v":33},{"c":"´«ø","t":"word","k":"7:33","v":33},{"c":"´«£","t":"word","k":"7:33","v":33},{"c":"´«Ø","t":"end","k":"7:33","v":33},{"c":"´«×","t":"word","k":"7:34","v":34},{"c":"´«ƒ","t":"word","k":"7:34","v":34},{"c":"´«á´«í","t":"word","k":"7:34","v":34}],"8":[{"c":"´«ó","t":"word","k":"7:34","v":34},{"c":"´«ú","t":"word","k":"7:34","v":34},{"c":"´«ñ","t":"word","k":"7:34","v":34},{"c":"´«Ñ","t":"word","k":"7:34","v":34},{"c":"´«ª","t":"word","k":"7:34","v":34},{"c":"´«º´«¿","t":"word","k":"7:34","v":34},{"c":"´«®","t":"word","k":"7:34","v":34},{"c":"´«¬","t":"word","k":"7:34","v":34},{"c":"´«½","t":"end","k":"7:34","v":34}],"9":[{"c":"´«¼","t":"word","k":"7:35","v":35},{"c":"´«¡","t":"word","k":"7:35","v":35},{"c":"´««","t":"word","k":"7:35","v":35},{"c":"´«»","t":"word","k":"7:35","v":35},{"c":"´«░","t":"word","k":"7:35","v":35},{"c":"´«▒","t":"word","k":"7:35","v":35},{"c":"´»ô","t":"word","k":"7:35","v":35},{"c":"´»ö","t":"word","k":"7:35","v":35},{"c":"´»ò´»û","t":"word","k":"7:35","v":35},{"c":"´»ù","t":"word","k":"7:35","v":35}],"10":[{"c":"´»ÿ","t":"word","k":"7:35","v":35},{"c":"´»Ö","t":"word","k":"7:35","v":35},{"c":"´»Ü","t":"word","k":"7:35","v":35},{"c":"´»ø","t":"word","k":"7:35","v":35},{"c":"´»£","t":"word","k":"7:35","v":35},{"c":"´»Ø","t":"word","k":"7:35","v":35},{"c":"´»×","t":"word","k":"7:35","v":35},{"c":"´»ƒ","t":"word","k":"7:35","v":35},{"c":"´»á","t":"end","k":"7:35","v":35},{"c":"´»í","t":"word","k":"7:36","v":36}],"11":[{"c":"´»ó","t":"word","k":"7:36","v":36},{"c":"´»ú","t":"word","k":"7:36","v":36},{"c":"´»ñ","t":"word","k":"7:36","v":36},{"c":"´»Ñ","t":"word","k":"7:36","v":36},{"c":"´»ª","t":"word","k":"7:36","v":36},{"c":"´»º","t":"word","k":"7:36","v":36},{"c":"´»¿´»®","t":"word","k":"7:36","v":36},{"c":"´»¬","t":"word","k":"7:36","v":36}],"12":[{"c":"´»½","t":"word","k":"7:36","v":36},{"c":"´»¼","t":"word","k":"7:36","v":36},{"c":"´»¡","t":"end","k":"7:36","v":36},{"c":"´»«","t":"word","k":"7:37","v":37},{"c":"´»»","t":"word","k":"7:37","v":37},{"c":"´»░","t":"word","k":"7:37","v":37},{"c":"´»▒","t":"word","k":"7:37","v":37},{"c":"´»▓","t":"word","k":"7:37","v":37},{"c":"´»│","t":"word","k":"7:37","v":37},{"c":"´»┤","t":"word","k":"7:37","v":37},{"c":"´»Á","t":"word","k":"7:37","v":37},{"c":"´»Â","t":"word","k":"7:37","v":37}],"13":[{"c":"´»À´»©","t":"word","k":"7:37","v":37},{"c":"´»╣","t":"word","k":"7:37","v":37},{"c":"´»║","t":"word","k":"7:37","v":37},{"c":"´»╗","t":"word","k":"7:37","v":37},{"c":"´»╝","t":"word","k":"7:37","v":37},{"c":"´»¢´»¥","t":"word","k":"7:37","v":37},{"c":"´»┐","t":"word","k":"7:37","v":37},{"c":"´░Ç","t":"word","k":"7:37","v":37},{"c":"´░ü","t":"word","k":"7:37","v":37}],"14":[{"c":"´░é","t":"word","k":"7:37","v":37},{"c":"´░â","t":"word","k":"7:37","v":37},{"c":"´░ä","t":"word","k":"7:37","v":37},{"c":"´░à","t":"word","k":"7:37","v":37},{"c":"´░å","t":"word","k":"7:37","v":37},{"c":"´░ç","t":"word","k":"7:37","v":37},{"c":"´░ê","t":"word","k":"7:37","v":37},{"c":"´░ë","t":"word","k":"7:37","v":37},{"c":"´░è","t":"word","k":"7:37","v":37},{"c":"´░ï´░î","t":"word","k":"7:37","v":37}],"15":[{"c":"´░ì","t":"word","k":"7:37","v":37},{"c":"´░Ä","t":"word","k":"7:37","v":37},{"c":"´░Å","t":"word","k":"7:37","v":37},{"c":"´░É","t":"word","k":"7:37","v":37},{"c":"´░æ","t":"word","k":"7:37","v":37},{"c":"´░Æ","t":"word","k":"7:37","v":37},{"c":"´░ô","t":"word","k":"7:37","v":37},{"c":"´░ö","t":"word","k":"7:37","v":37},{"c":"´░ò","t":"word","k":"7:37","v":37},{"c":"´░û","t":"end","k":"7:37","v":37}]}}