{"page":257,"lines":{"1":[{"c":"´¡æ","t":"word","k":"14:11","v":11},{"c":"´¡Æ","t":"word","k":"14:11","v":11},{"c":"´¡ô","t":"word","k":"14:11","v":11},{"c":"´¡ö","t":"word","k":"14:11","v":11},{"c":"´¡ò","t":"word","k":"14:11","v":11},{"c":"´¡û","t":"word","k":"14:11","v":11},{"c":"´¡ù","t":"word","k":"14:11","v":11},{"c":"´¡İ","t":"word","k":"14:11","v":11},{"c":"´¡Ö","t":"word","k":"14:11","v":11},{"c":"´¡Ü","t":"word","k":"14:11","v":11}],"2":[{"c":"´¡ø","t":"word","k":"14:11","v":11},{"c":"´¡£","t":"word","k":"14:11","v":11},{"c":"´¡Ø","t":"word","k":"14:11","v":11},{"c":"´¡Ş","t":"word","k":"14:11","v":11},{"c":"´¡ş","t":"word","k":"14:11","v":11},{"c":"´¡á´¡í","t":"word","k":"14:11","v":11},{"c":"´¡ó","t":"word","k":"14:11","v":11},{"c":"´¡ú","t":"word","k":"14:11","v":11},{"c":"´¡ñ","t":"word","k":"14:11","v":11},{"c":"´¡Ñ","t":"word","k":"14:11","v":11},{"c":"´¡Ğ","t":"word","k":"14:11","v":11}],"3":[{"c":"´¡ğ","t":"word","k":"14:11","v":11},{"c":"´¡¿","t":"word","k":"14:11","v":11},{"c":"´¡®","t":"word","k":"14:11","v":11},{"c":"´¡¬´¡½","t":"word","k":"14:11","v":11},{"c":"´¡¼","t":"word","k":"14:11","v":11},{"c":"´¡¡","t":"word","k":"14:11","v":11},{"c":"´¡«","t":"word","k":"14:11","v":11},{"c":"´¡»","t":"word","k":"14:11","v":11}],"4":[{"c":"´¡░","t":"end","k":"14:11","v":11},{"c":"´¡▒","t":"word","k":"14:12","v":12},{"c":"´¡▓","t":"word","k":"14:12","v":12},{"c":"´¡│","t":"word","k":"14:12","v":12},{"c":"´¡┤","t":"word","k":"14:12","v":12},{"c":"´¡Á","t":"word","k":"14:12","v":12},{"c":"´¡Â","t":"word","k":"14:12","v":12},{"c":"´¡À","t":"word","k":"14:12","v":12},{"c":"´¡©","t":"word","k":"14:12","v":12},{"c":"´¡╣´¡║","t":"word","k":"14:12","v":12}],"5":[{"c":"´¡╗","t":"word","k":"14:12","v":12},{"c":"´¡╝","t":"word","k":"14:12","v":12},{"c":"´¡¢","t":"word","k":"14:12","v":12},{"c":"´¡¥´¡┐","t":"word","k":"14:12","v":12},{"c":"´«Ç","t":"word","k":"14:12","v":12},{"c":"´«ü","t":"word","k":"14:12","v":12},{"c":"´«é","t":"word","k":"14:12","v":12},{"c":"´«â","t":"word","k":"14:12","v":12}],"6":[{"c":"´«ä","t":"end","k":"14:12","v":12},{"c":"´«à","t":"word","k":"14:13","v":13},{"c":"´«å","t":"word","k":"14:13","v":13},{"c":"´«ç","t":"word","k":"14:13","v":13},{"c":"´«ê","t":"word","k":"14:13","v":13},{"c":"´«ë","t":"word","k":"14:13","v":13},{"c":"´«è","t":"word","k":"14:13","v":13}],"7":[{"c":"´«ï","t":"word","k":"14:13","v":13},{"c":"´«î","t":"word","k":"14:13","v":13},{"c":"´«ı","t":"word","k":"14:13","v":13},{"c":"´«Ä","t":"word","k":"14:13","v":13},{"c":"´«Å´«É","t":"word","k":"14:13","v":13},{"c":"´«æ","t":"word","k":"14:13","v":13},{"c":"´«Æ","t":"word","k":"14:13","v":13},{"c":"´«ô","t":"word","k":"14:13","v":13},{"c":"´«ö","t":"word","k":"14:13","v":13}],"8":[{"c":"´«ò","t":"word","k":"14:13","v":13},{"c":"´«û","t":"end","k":"14:13","v":13},{"c":"´«ù","t":"word","k":"14:14","v":14},{"c":"´«İ","t":"word","k":"14:14","v":14},{"c":"´«Ö","t":"word","k":"14:14","v":14},{"c":"´«Ü´«ø","t":"word","k":"14:14","v":14}],"9":[{"c":"´«£","t":"word","k":"14:14","v":14},{"c":"´«Ø","t":"word","k":"14:14","v":14},{"c":"´«Ş","t":"word","k":"14:14","v":14},{"c":"´«ş","t":"word","k":"14:14","v":14},{"c":"´«á","t":"word","k":"14:14","v":14},{"c":"´«í","t":"word","k":"14:14","v":14},{"c":"´«ó","t":"end","k":"14:14","v":14},{"c":"´«ú","t":"word","k":"14:15","v":15}],"10":[{"c":"´«ñ","t":"word","k":"14:15","v":15},{"c":"´«Ñ","t":"word","k":"14:15","v":15},{"c":"´«Ğ","t":"word","k":"14:15","v":15},{"c":"´«ğ","t":"word","k":"14:15","v":15},{"c":"´«¿","t":"end","k":"14:15","v":15},{"c":"´«®","t":"word","k":"14:16","v":16},{"c":"´«¬","t":"word","k":"14:16","v":16},{"c":"´«½","t":"word","k":"14:16","v":16},{"c":"´«¼","t":"word","k":"14:16","v":16}],"11":[{"c":"´«¡","t":"word","k":"14:16","v":16},{"c":"´««","t":"word","k":"14:16","v":16},{"c":"´«»","t":"word","k":"14:16","v":16},{"c":"´«░","t":"end","k":"14:16","v":16},{"c":"´«▒","t":"word","k":"14:17","v":17},{"c":"´»ô","t":"word","k":"14:17","v":17},{"c":"´»ö","t":"word","k":"14:17","v":17},{"c":"´»ò","t":"word","k":"14:17","v":17}],"12":[{"c":"´»û","t":"word","k":"14:17","v":17},{"c":"´»ù","t":"word","k":"14:17","v":17},{"c":"´»İ","t":"word","k":"14:17","v":17},{"c":"´»Ö","t":"word","k":"14:17","v":17},{"c":"´»Ü","t":"word","k":"14:17","v":17},{"c":"´»ø","t":"word","k":"14:17","v":17},{"c":"´»£","t":"word","k":"14:17","v":17},{"c":"´»Ø´»Ş","t":"word","k":"14:17","v":17},{"c":"´»ş","t":"word","k":"14:17","v":17}],"13":[{"c":"´»á","t":"word","k":"14:17","v":17},{"c":"´»í","t":"word","k":"14:17","v":17},{"c":"´»ó","t":"word","k":"14:17","v":17},{"c":"´»ú","t":"end","k":"14:17","v":17},{"c":"´»ñ","t":"word","k":"14:18","v":18},{"c":"´»Ñ","t":"word","k":"14:18","v":18},{"c":"´»Ğ","t":"word","k":"14:18","v":18},{"c":"´»ğ´»¿","t":"word","k":"14:18","v":18}],"14":[{"c":"´»®","t":"word","k":"14:18","v":18},{"c":"´»¬","t":"word","k":"14:18","v":18},{"c":"´»½","t":"word","k":"14:18","v":18},{"c":"´»¼","t":"word","k":"14:18","v":18},{"c":"´»¡","t":"word","k":"14:18","v":18},{"c":"´»«","t":"word","k":"14:18","v":18},{"c":"´»»","t":"word","k":"14:18","v":18},{"c":"´»░´»▒","t":"word","k":"14:18","v":18},{"c":"´»▓","t":"word","k":"14:18","v":18},{"c":"´»│","t":"word","k":"14:18","v":18}],"15":[{"c":"´»┤","t":"word","k":"14:18","v":18},{"c":"´»Á","t":"word","k":"14:18","v":18},{"c":"´»Â","t":"word","k":"14:18","v":18},{"c":"´»À´»©","t":"word","k":"14:18","v":18},{"c":"´»╣","t":"word","k":"14:18","v":18},{"c":"´»║","t":"word","k":"14:18","v":18},{"c":"´»╗","t":"word","k":"14:18","v":18},{"c":"´»╝","t":"word","k":"14:18","v":18},{"c":"´»¢","t":"end","k":"14:18","v":18}]}}