{
  "asma": [
    { "name": "اللَّهُ", "meaning": "الجامِعُ لِصِفاتِ الكَمال" },
    { "name": "الرَّحْمَٰنُ", "meaning": "الواسِعُ الرَّحمَةِ بِالخَلقِ جَميعاً" },
    { "name": "الرَّحِيمُ", "meaning": "الرَّحيمُ بِالمُؤمِنينَ خاصَّةً" },
    { "name": "الْمَلِكُ", "meaning": "المالِكُ المُتَصَرِّفُ في كُلِّ شَيء" },
    { "name": "الْقُدُّوسُ", "meaning": "المُنَزَّهُ عَنْ كُلِّ نَقص" },
    { "name": "السَّلَامُ", "meaning": "السالِمُ مِنْ كُلِّ عَيب" },
    { "name": "الْمُؤْمِنُ", "meaning": "مانِحُ الأمانِ لِخَلقِه" },
    { "name": "الْمُهَيْمِنُ", "meaning": "الرَّقيبُ الحافِظُ على خَلقِه" },
    { "name": "الْعَزِيزُ", "meaning": "الغالِبُ الَّذي لا يُغلَب" },
    { "name": "الْجَبَّارُ", "meaning": "القاهِرُ النافِذُ مَشيئَتُه" },
    { "name": "الْمُتَكَبِّرُ", "meaning": "المُتَعالي عَنْ صِفاتِ الخَلق" },
    { "name": "الْخَالِقُ", "meaning": "المُقَدِّرُ المُوجِدُ لِلأشياء" },
    { "name": "الْبَارِئُ", "meaning": "المُنشِئُ لِلخَلقِ مِنَ العَدَم" },
    { "name": "الْمُصَوِّرُ", "meaning": "المُشَكِّلُ لِلخَلقِ كَما يَشاء" },
    { "name": "الْغَفَّارُ", "meaning": "كَثيرُ المَغفِرَةِ لِلذُّنوب" },
    { "name": "الْقَهَّارُ", "meaning": "القاهِرُ لِكُلِّ شَيء" },
    { "name": "الْوَهَّابُ", "meaning": "كَثيرُ العَطاءِ بِلا عِوَض" },
    { "name": "الرَّزَّاقُ", "meaning": "المُتَكَفِّلُ بِأرزاقِ الخَلق" },
    { "name": "الْفَتَّاحُ", "meaning": "الفاتِحُ لِأبوابِ الرَّحمَةِ والرِّزق" },
    { "name": "الْعَلِيمُ", "meaning": "العالِمُ بِكُلِّ شَيء" },
    { "name": "الْقَابِضُ", "meaning": "القابِضُ لِلرِّزقِ بِحِكمَة" },
    { "name": "الْبَاسِطُ", "meaning": "الباسِطُ لِلرِّزقِ والرَّحمَة" },
    { "name": "الْخَافِضُ", "meaning": "الخافِضُ لِلمُتَكَبِّرين" },
    { "name": "الرَّافِعُ", "meaning": "الرافِعُ لِأوليائِهِ بِالطاعَة" },
    { "name": "الْمُعِزُّ", "meaning": "المانِحُ العِزَّةَ لِمَن يَشاء" },
    { "name": "الْمُذِلُّ", "meaning": "المُذِلُّ لِمَن يَشاءُ بِعَدلِه" },
    { "name": "السَّمِيعُ", "meaning": "السامِعُ لِكُلِّ الأصوات" },
    { "name": "الْبَصِيرُ", "meaning": "المُبصِرُ لِكُلِّ الأشياء" },
    { "name": "الْحَكَمُ", "meaning": "الحاكِمُ العَدلُ بَينَ الخَلق" },
    { "name": "الْعَدْلُ", "meaning": "الكامِلُ في عَدلِه" },
    { "name": "اللَّطِيفُ", "meaning": "الرَّفيقُ بِعِبادِهِ، العالِمُ بِالخَفايا" },
    { "name": "الْخَبِيرُ", "meaning": "العالِمُ بِبَواطِنِ الأمور" },
    { "name": "الْحَلِيمُ", "meaning": "الَّذي لا يُعَجِّلُ بِالعُقوبَة" },
    { "name": "الْعَظِيمُ", "meaning": "العَظيمُ في ذاتِهِ وصِفاتِه" },
    { "name": "الْغَفُورُ", "meaning": "السَّاتِرُ الغافِرُ لِلذُّنوب" },
    { "name": "الشَّكُورُ", "meaning": "المُجازي على القَليلِ بِالكَثير" },
    { "name": "الْعَلِيُّ", "meaning": "العالي فَوقَ كُلِّ شَيء" },
    { "name": "الْكَبِيرُ", "meaning": "الأكبَرُ مِنْ كُلِّ شَيء" },
    { "name": "الْحَفِيظُ", "meaning": "الحافِظُ لِخَلقِهِ وأعمالِهِم" },
    { "name": "الْمُقِيتُ", "meaning": "المُقَدِّرُ لِلأقواتِ والحافِظُ لَها" },
    { "name": "الْحَسِيبُ", "meaning": "الكافي عِبادَهُ، المُحاسِبُ لَهُم" },
    { "name": "الْجَلِيلُ", "meaning": "العَظيمُ ذو الجَلال" },
    { "name": "الْكَرِيمُ", "meaning": "كَثيرُ الخَيرِ والعَطاء" },
    { "name": "الرَّقِيبُ", "meaning": "المُراقِبُ لِكُلِّ شَيء" },
    { "name": "الْمُجِيبُ", "meaning": "المُجيبُ لِدُعاءِ عِبادِه" },
    { "name": "الْوَاسِعُ", "meaning": "الواسِعُ في عِلمِهِ ورَحمَتِه" },
    { "name": "الْحَكِيمُ", "meaning": "المُحكِمُ لِأمورِهِ بِحِكمَة" },
    { "name": "الْوَدُودُ", "meaning": "المُحِبُّ لِأوليائِهِ، المَحبوب" },
    { "name": "الْمَجِيدُ", "meaning": "العَظيمُ الكَريمُ المَجيد" },
    { "name": "الْبَاعِثُ", "meaning": "الباعِثُ لِلخَلقِ يَومَ القِيامَة" },
    { "name": "الشَّهِيدُ", "meaning": "الشاهِدُ على كُلِّ شَيء" },
    { "name": "الْحَقُّ", "meaning": "الثابِتُ الَّذي لا يَزول" },
    { "name": "الْوَكِيلُ", "meaning": "الكَفيلُ بِأمورِ خَلقِه" },
    { "name": "الْقَوِيُّ", "meaning": "الكامِلُ القُدرَةِ والقُوَّة" },
    { "name": "الْمَتِينُ", "meaning": "الشَّديدُ القُوَّةِ بِلا تَعَب" },
    { "name": "الْوَلِيُّ", "meaning": "النَّاصِرُ المُتَوَلِّي لِأوليائِه" },
    { "name": "الْحَمِيدُ", "meaning": "المَحمودُ في كُلِّ حال" },
    { "name": "الْمُحْصِي", "meaning": "العالِمُ بِعَدَدِ كُلِّ شَيء" },
    { "name": "الْمُبْدِئُ", "meaning": "البادِئُ لِلخَلقِ بِلا مِثال" },
    { "name": "الْمُعِيدُ", "meaning": "المُعيدُ لِلخَلقِ بَعدَ الفَناء" },
    { "name": "الْمُحْيِي", "meaning": "المانِحُ لِلحَياة" },
    { "name": "الْمُمِيتُ", "meaning": "المُقَدِّرُ لِلمَوت" },
    { "name": "الْحَيُّ", "meaning": "الحَيُّ الَّذي لا يَموت" },
    { "name": "الْقَيُّومُ", "meaning": "القائِمُ بِنَفسِهِ، المُقيمُ لِغَيرِه" },
    { "name": "الْوَاجِدُ", "meaning": "الغَنِيُّ الَّذي لا يُعوِزُهُ شَيء" },
    { "name": "الْمَاجِدُ", "meaning": "العَظيمُ الكَريمُ المَجيد" },
    { "name": "الْوَاحِدُ", "meaning": "المُتَفَرِّدُ بِالألوهِيَّة" },
    { "name": "الْأَحَدُ", "meaning": "الفَردُ الَّذي لا نَظيرَ لَه" },
    { "name": "الصَّمَدُ", "meaning": "المَقصودُ في الحَوائِجِ دائِماً" },
    { "name": "الْقَادِرُ", "meaning": "القادِرُ على كُلِّ شَيء" },
    { "name": "الْمُقْتَدِرُ", "meaning": "الكامِلُ القُدرَة" },
    { "name": "الْمُقَدِّمُ", "meaning": "المُقَدِّمُ لِما يَشاءُ بِحِكمَة" },
    { "name": "الْمُؤَخِّرُ", "meaning": "المُؤَخِّرُ لِما يَشاءُ بِحِكمَة" },
    { "name": "الْأَوَّلُ", "meaning": "الَّذي لَيسَ قَبلَهُ شَيء" },
    { "name": "الْآخِرُ", "meaning": "الَّذي لَيسَ بَعدَهُ شَيء" },
    { "name": "الظَّاهِرُ", "meaning": "الظاهِرُ فَوقَ كُلِّ شَيء" },
    { "name": "الْبَاطِنُ", "meaning": "العالِمُ بِالخَفايا، الأقرَب" },
    { "name": "الْوَالِي", "meaning": "المُتَوَلِّي لِأمورِ الخَلق" },
    { "name": "الْمُتَعَالِي", "meaning": "المُنَزَّهُ عَنْ صِفاتِ الخَلق" },
    { "name": "الْبَرُّ", "meaning": "الواسِعُ البِرِّ والإحسان" },
    { "name": "التَّوَّابُ", "meaning": "كَثيرُ قَبولِ التَّوبَة" },
    { "name": "الْمُنْتَقِمُ", "meaning": "المُعاقِبُ لِلعُصاةِ بِعَدل" },
    { "name": "الْعَفُوُّ", "meaning": "كَثيرُ العَفوِ عَنِ الذُّنوب" },
    { "name": "الرَّؤُوفُ", "meaning": "الشَّديدُ الرَّحمَةِ بِعِبادِه" },
    { "name": "مَالِكُ الْمُلْكِ", "meaning": "المُتَصَرِّفُ في مُلكِهِ كَيفَ يَشاء" },
    { "name": "ذُو الْجَلَالِ وَالْإِكْرَامِ", "meaning": "صاحِبُ العَظَمَةِ والفَضل" },
    { "name": "الْمُقْسِطُ", "meaning": "العادِلُ في حُكمِه" },
    { "name": "الْجَامِعُ", "meaning": "الجامِعُ لِلخَلقِ يَومَ القِيامَة" },
    { "name": "الْغَنِيُّ", "meaning": "الغَنِيُّ عَنْ كُلِّ ما سِواه" },
    { "name": "الْمُغْنِي", "meaning": "المُغني لِعِبادِهِ مِنْ فَضلِه" },
    { "name": "الْمَانِعُ", "meaning": "المانِعُ ما يَشاءُ بِحِكمَة" },
    { "name": "الضَّارُّ", "meaning": "لا يَقَعُ ضُرٌّ إلّا بِإذنِه" },
    { "name": "النَّافِعُ", "meaning": "لا يَقَعُ نَفعٌ إلّا بِإذنِه" },
    { "name": "النُّورُ", "meaning": "نورُ السَّماواتِ والأرض" },
    { "name": "الْهَادِي", "meaning": "الهادي لِعِبادِهِ إلى الحَقّ" },
    { "name": "الْبَدِيعُ", "meaning": "المُبدِعُ لِلخَلقِ بِلا مِثال" },
    { "name": "الْبَاقِي", "meaning": "الدائِمُ الَّذي لا يَفنى" },
    { "name": "الْوَارِثُ", "meaning": "الباقي بَعدَ فَناءِ الخَلق" },
    { "name": "الرَّشِيدُ", "meaning": "المُرشِدُ لِخَلقِهِ بِحِكمَة" },
    { "name": "الصَّبُورُ", "meaning": "الَّذي لا يُعَجِّلُ بِالعُقوبَة" }
  ],
  "extra": [
    { "text": "وَقَالَ رَبُّكُمُ ادْعُونِي أَسْتَجِبْ لَكُمْ", "source": "غافر ٦٠" },
    { "text": "حَسْبُنَا اللَّهُ وَنِعْمَ الْوَكِيلُ", "source": "آل عمران ١٧٣" },
    { "text": "وَهُوَ مَعَكُمْ أَيْنَ مَا كُنتُمْ", "source": "الحديد ٤" },
    { "text": "إِنَّ اللَّهَ مَعَ الصَّابِرِينَ", "source": "البقرة ١٥٣" },
    { "text": "وَنُنَزِّلُ مِنَ الْقُرْآنِ مَا هُوَ شِفَاءٌ وَرَحْمَةٌ لِّلْمُؤْمِنِينَ", "source": "الإسراء ٨٢" },
    { "text": "يَا أَيُّهَا الَّذِينَ آمَنُوا اذْكُرُوا اللَّهَ ذِكْرًا كَثِيرًا", "source": "الأحزاب ٤١" },
    { "text": "وَاللَّهُ يُحِبُّ الْمُحْسِنِينَ", "source": "آل عمران ١٣٤" },
    { "text": "رَبَّنَا آتِنَا فِي الدُّنْيَا حَسَنَةً وَفِي الْآخِرَةِ حَسَنَةً وَقِنَا عَذَابَ النَّارِ", "source": "البقرة ٢٠١" },
    { "text": "رَبِّ اشْرَحْ لِي صَدْرِي وَيَسِّرْ لِي أَمْرِي", "source": "طه ٢٥-٢٦" },
    { "text": "رَبِّ زِدْنِي عِلْمًا", "source": "طه ١١٤" },
    { "text": "لَا إِلَهَ إِلَّا أَنتَ سُبْحَانَكَ إِنِّي كُنتُ مِنَ الظَّالِمِينَ", "source": "الأنبياء ٨٧" },
    { "text": "رَبَّنَا لَا تُؤَاخِذْنَا إِن نَّسِينَا أَوْ أَخْطَأْنَا", "source": "البقرة ٢٨٦" },
    { "text": "اللَّهُمَّ أَعِنِّي عَلَى ذِكْرِكَ وَشُكْرِكَ وَحُسْنِ عِبَادَتِكَ", "source": "رواه أبو داود" },
    { "text": "اللَّهُمَّ إِنِّي أَسْأَلُكَ الْهُدَى وَالتُّقَى وَالْعَفَافَ وَالْغِنَى", "source": "رواه مسلم" },
    { "text": "اللَّهُمَّ إِنَّكَ عَفُوٌّ كَرِيمٌ تُحِبُّ الْعَفْوَ فَاعْفُ عَنِّي", "source": "رواه الترمذي" },
    { "text": "اللَّهُمَّ بَارِكْ لَنَا فِيمَا رَزَقْتَنَا وَقِنَا عَذَابَ النَّارِ", "source": "دعاء مأثور" },

    { "text": "وَإِذَا سَأَلَكَ عِبَادِي عَنِّي فَإِنِّي قَرِيبٌ أُجِيبُ دَعْوَةَ الدَّاعِ إِذَا دَعَانِ", "source": "البقرة ١٨٦" },
    { "text": "وَاسْتَعِينُوا بِالصَّبْرِ وَالصَّلَاةِ", "source": "البقرة ٤٥" },
    { "text": "إِنَّ اللَّهَ يَأْمُرُ بِالْعَدْلِ وَالْإِحْسَانِ وَإِيتَاءِ ذِي الْقُرْبَىٰ", "source": "النحل ٩٠" },
    { "text": "وَتَعَاوَنُوا عَلَى الْبِرِّ وَالتَّقْوَىٰ", "source": "المائدة ٢" },
    { "text": "إِنَّمَا يُوَفَّى الصَّابِرُونَ أَجْرَهُم بِغَيْرِ حِسَابٍ", "source": "الزمر ١٠" },
    { "text": "فَاسْتَبِقُوا الْخَيْرَاتِ", "source": "البقرة ١٤٨" },
    { "text": "إِنَّ اللَّهَ لَا يُضِيعُ أَجْرَ الْمُحْسِنِينَ", "source": "التوبة ١٢٠" },
    { "text": "وَمَن يَعْمَلْ مِثْقَالَ ذَرَّةٍ خَيْرًا يَرَهُ", "source": "الزلزلة ٧" },

    { "text": "الدِّينُ النَّصِيحَةُ", "source": "رواه مسلم" },
    { "text": "المُسْلِمُ مَنْ سَلِمَ المُسْلِمُونَ مِنْ لِسَانِهِ وَيَدِهِ", "source": "متفق عليه" },
    { "text": "مَنْ كَانَ يُؤْمِنُ بِاللَّهِ وَاليَوْمِ الآخِرِ فَلْيَقُلْ خَيْرًا أَوْ لِيَصْمُتْ", "source": "متفق عليه" },
    { "text": "لَا يُؤْمِنُ أَحَدُكُمْ حَتَّى يُحِبَّ لِأَخِيهِ مَا يُحِبُّ لِنَفْسِهِ", "source": "متفق عليه" },
    { "text": "اتَّقِ اللَّهَ حَيْثُمَا كُنْتَ، وَأَتْبِعِ السَّيِّئَةَ الحَسَنَةَ تَمْحُهَا", "source": "رواه الترمذي" },
    { "text": "مَنْ سَلَكَ طَرِيقًا يَلْتَمِسُ فِيهِ عِلْمًا سَهَّلَ اللَّهُ لَهُ بِهِ طَرِيقًا إِلَى الجَنَّةِ", "source": "رواه مسلم" },
    { "text": "تَبَسُّمُكَ فِي وَجْهِ أَخِيكَ صَدَقَةٌ", "source": "رواه الترمذي" },
    { "text": "الطُّهُورُ شَطْرُ الإِيمَانِ", "source": "رواه مسلم" },

    { "text": "سُبْحَانَ اللَّهِ وَالحَمْدُ لِلَّهِ وَلَا إِلَهَ إِلَّا اللَّهُ وَاللَّهُ أَكْبَرُ", "source": "الباقيات الصالحات" },
    { "text": "رَضِيتُ بِاللَّهِ رَبًّا، وَبِالإِسْلَامِ دِينًا، وَبِمُحَمَّدٍ ﷺ نَبِيًّا", "source": "رواه أبو داود" },
    { "text": "اللَّهُمَّ أَنْتَ رَبِّي لَا إِلَهَ إِلَّا أَنْتَ، خَلَقْتَنِي وَأَنَا عَبْدُكَ", "source": "سيد الاستغفار" },
    { "text": "بِسْمِ اللَّهِ الَّذِي لَا يَضُرُّ مَعَ اسْمِهِ شَيْءٌ فِي الأَرْضِ وَلَا فِي السَّمَاءِ", "source": "رواه أبو داود" },
    { "text": "يَا حَيُّ يَا قَيُّومُ بِرَحْمَتِكَ أَسْتَغِيثُ", "source": "رواه الترمذي" },
    { "text": "لَا إِلَهَ إِلَّا اللَّهُ العَظِيمُ الحَلِيمُ، لَا إِلَهَ إِلَّا اللَّهُ رَبُّ العَرْشِ العَظِيمِ", "source": "متفق عليه" },
    { "text": "سُبْحَانَ اللَّهِ عَدَدَ خَلْقِهِ، وَرِضَا نَفْسِهِ، وَزِنَةَ عَرْشِهِ، وَمِدَادَ كَلِمَاتِهِ", "source": "رواه مسلم" },
    { "text": "اللَّهُمَّ صَلِّ وَسَلِّمْ وَبَارِكْ عَلَى نَبِيِّنَا مُحَمَّدٍ", "source": "صلاة على النبي ﷺ" }
  ]
}
